Metadata-Version: 2.1
Name: cmdstanpy
Version: 1.2.4
Summary: Python interface to CmdStan
Author: Stan Dev Team
License: BSD-3-Clause
Project-URL: Homepage, https://github.com/stan-dev/cmdstanpy
Project-URL: Bug Tracker, https://github.com/stan-dev/cmdstanpy/issues
Classifier: Programming Language :: Python :: 3
Classifier: License :: OSI Approved :: BSD License
Classifier: Operating System :: OS Independent
Classifier: Development Status :: 5 - Production/Stable
Classifier: Intended Audience :: Science/Research
Classifier: Natural Language :: English
Classifier: Programming Language :: Python
Classifier: Topic :: Scientific/Engineering :: Information Analysis
Requires-Python: >=3.8
License-File: LICENSE.md
Requires-Dist: pandas
Requires-Dist: numpy>=1.21
Requires-Dist: tqdm
Requires-Dist: stanio<2.0.0,>=0.4.0
Provides-Extra: all
Requires-Dist: xarray; extra == "all"
Provides-Extra: test
Requires-Dist: flake8; extra == "test"
Requires-Dist: pylint; extra == "test"
Requires-Dist: pytest; extra == "test"
Requires-Dist: pytest-cov; extra == "test"
Requires-Dist: pytest-order; extra == "test"
Requires-Dist: mypy; extra == "test"
Requires-Dist: xarray; extra == "test"
Provides-Extra: docs
Requires-Dist: sphinx<6,>5; extra == "docs"
Requires-Dist: pydata-sphinx-theme<0.9; extra == "docs"
Requires-Dist: nbsphinx; extra == "docs"
Requires-Dist: ipython; extra == "docs"
Requires-Dist: ipykernel; extra == "docs"
Requires-Dist: ipywidgets; extra == "docs"
Requires-Dist: sphinx-copybutton; extra == "docs"
Requires-Dist: xarray; extra == "docs"
Requires-Dist: matplotlib; extra == "docs"
